mkdocs_sqlite_console/__init__.py
mkdocs_sqlite_console/plugin.py
mkdocs_sqlite_console/css/sqlite_ide.css
mkdocs_sqlite_console/js/material-tabbed-fix.js
mkdocs_sqlite_console/js/sql-wasm.wasm
mkdocs_sqlite_console/js/sqlite_ide.js
mkdocs_sqlite_console/js/worker.sql-wasm.js
mkdocs_sqlite_console-2.1.2.dist-info/licenses/LICENSE
mkdocs_sqlite_console-2.1.2.dist-info/METADATA
mkdocs_sqlite_console-2.1.2.dist-info/WHEEL
mkdocs_sqlite_console-2.1.2.dist-info/entry_points.txt
mkdocs_sqlite_console-2.1.2.dist-info/top_level.txt
mkdocs_sqlite_console-2.1.2.dist-info/RECORD
