Metadata-Version: 2.4
Name: mkdocs-sqlite-console
Version: 2.1.2
Summary: Mkdocs-SQLite-Console est un plugin pour MkDocs, qui permet d'afficher un IDE SQL (SQLite) permettant d'exécuter du code.
Author-email: Rafael Lopez <rafael.lopez@universite-paris-saclay.fr>, Frédéric Zinelli <frederic.zinelli@gmail.com>
License: MIT
Project-URL: documentation, https://epithumia.github.io/mkdocs-sqlite-console/
Project-URL: source, https://github.com/Epithumia/mkdocs-sqlite-console
Keywords: mkdocs,sql,sqlite
Classifier: License :: OSI Approved :: MIT License
Classifier: Programming Language :: Python
Classifier: Programming Language :: Python :: 3 :: Only
Classifier: Programming Language :: Python :: 3.9
Classifier: Programming Language :: Python :: 3.10
Classifier: Programming Language :: Python :: 3.11
Classifier: Programming Language :: Python :: 3.12
Classifier: Programming Language :: Python :: 3.13
Requires-Python: >=3.9
License-File: LICENSE
Requires-Dist: mkdocs>=1.0.4
Provides-Extra: docs
Requires-Dist: mkdocs>=1.0.4; extra == "docs"
Requires-Dist: mkdocs-material>=6.0.0; extra == "docs"
Dynamic: license-file
